kmsauth/__init__.py
kmsauth/services.py
kmsauth/utils/__init__.py
kmsauth/utils/lru.py
kmsauth-0.6.3.dist-info/LICENSE
kmsauth-0.6.3.dist-info/METADATA
kmsauth-0.6.3.dist-info/WHEEL
kmsauth-0.6.3.dist-info/top_level.txt
kmsauth-0.6.3.dist-info/RECORD
